packageTest_Ljh/__init__.py
packageTest_Ljh/core.py
packageTest_Ljh-0.0.1.dist-info/METADATA
packageTest_Ljh-0.0.1.dist-info/WHEEL
packageTest_Ljh-0.0.1.dist-info/top_level.txt
packageTest_Ljh-0.0.1.dist-info/RECORD
