Metadata-Version: 2.1
Name: packageTest-Ljh
Version: 0.0.1
Summary: packageTesting
Home-page: https://github.com/Leejunho123/package_Ljh
Author: Leejunho123
Author-email: naix123451@gmail.com
License: MIT
Keywords: Deep Learning
Platform: UNKNOWN
Classifier: Programming Language :: Python :: 2.7
Classifier: Programming Language :: Python :: 3
Classifier: Programming Language :: Python :: 3.8
